diligent/__init__.py
diligent/_version.py
diligent/cli/__init__.py
diligent/cli/obs.py
diligent/cli/start.py
diligent/server/__init__.py
diligent/server/api.py
diligent/storage/__init__.py
diligent/storage/obs/__init__.py
diligent/storage/obs/client.py
diligent-0.0.5.dist-info/LICENSE
diligent-0.0.5.dist-info/METADATA
diligent-0.0.5.dist-info/WHEEL
diligent-0.0.5.dist-info/entry_points.txt
diligent-0.0.5.dist-info/top_level.txt
diligent-0.0.5.dist-info/zip-safe
diligent-0.0.5.dist-info/RECORD
