Metadata-Version: 2.1
Name: diligent
Version: 0.0.5
Summary: markdown and image serve base on cloud storage
Home-page: https://github.com/lipicoder/diligent
Author: lipi
Author-email: lipi <lipicoder@qq.com>
Project-URL: Bug Tracker, https://github.com/lipicoder/diligent/issues
Project-URL: Homepage, https://github.com/lipicoder/diligent
Classifier: Programming Language :: Python :: 3
Classifier: License :: OSI Approved :: MIT License
Classifier: Operating System :: OS Independent
License-File: LICENSE
Requires-Dist: fastapi (==0.88.0)
Requires-Dist: click (==8.1.3)
Requires-Dist: esdk-obs-python (==3.22.2)
Requires-Dist: uvicorn (==0.20.0)
Requires-Dist: tomli ; python_version < "3.11"
